filectrl/__init__.py
filectrl-0.0.4.dist-info/METADATA
filectrl-0.0.4.dist-info/WHEEL
filectrl-0.0.4.dist-info/licenses/LICENSE
filectrl-0.0.4.dist-info/RECORD
