Metadata-Version: 2.1
Name: filectrl
Version: 0.0.4
Summary: File Controller
Project-URL: Homepage, https://github.com/chorong8883/filectrl
Author-email: Chor <chorong8883@gmail.com>
License-File: LICENSE
Keywords: file,file control,file controller,file ctrl,filectrl
Classifier: License :: OSI Approved :: MIT License
Classifier: Operating System :: MacOS
Classifier: Operating System :: POSIX :: Linux
Classifier: Programming Language :: Python :: 3.10
Requires-Python: >=3.10
